ol_social_auth/__init__.py
ol_social_auth/backends.py
ol_social_auth-0.2.0.dist-info/METADATA
ol_social_auth-0.2.0.dist-info/WHEEL
ol_social_auth-0.2.0.dist-info/licenses/LICENSE
ol_social_auth-0.2.0.dist-info/RECORD
