Metadata-Version: 2.4
Name: ol-social-auth
Version: 0.2.0
Summary: An Open edX plugin implementing MIT social auth backend
Author: MIT Office of Digital Learning
License-Expression: BSD-3-Clause
License-File: LICENSE
Keywords: Python,edx
Requires-Python: >=3.11
Requires-Dist: django>=4.0
Requires-Dist: social-auth-core>=4.5.4
